random-file-generator/__init__.py
random_file_generator/__init__.py
random_file_generator-0.0.3.dist-info/LICENSE
random_file_generator-0.0.3.dist-info/METADATA
random_file_generator-0.0.3.dist-info/WHEEL
random_file_generator-0.0.3.dist-info/top_level.txt
random_file_generator-0.0.3.dist-info/RECORD
